llvm_ir_dataset_utils/__init__.py
llvm_ir_dataset_utils/builders/__init__.py
llvm_ir_dataset_utils/builders/autoconf_builder.py
llvm_ir_dataset_utils/builders/builder.py
llvm_ir_dataset_utils/builders/cargo_builder.py
llvm_ir_dataset_utils/builders/cmake_builder.py
llvm_ir_dataset_utils/builders/julia_builder.jl
llvm_ir_dataset_utils/builders/julia_builder.py
llvm_ir_dataset_utils/builders/manual_builder.py
llvm_ir_dataset_utils/builders/spack_builder.py
llvm_ir_dataset_utils/builders/swift_builder.py
llvm_ir_dataset_utils/sources/git_source.py
llvm_ir_dataset_utils/sources/source.py
llvm_ir_dataset_utils/sources/tar_source.py
llvm_ir_dataset_utils/tools/__init__.py
llvm_ir_dataset_utils/tools/aggregate_build_sizes.py
llvm_ir_dataset_utils/tools/audit_licenses.py
llvm_ir_dataset_utils/tools/audit_package_list_licenses.py
llvm_ir_dataset_utils/tools/build_crate_from_repository.py
llvm_ir_dataset_utils/tools/build_julia_packages.py
llvm_ir_dataset_utils/tools/build_spack_package_from_list.py
llvm_ir_dataset_utils/tools/build_swift_packages.py
llvm_ir_dataset_utils/tools/collect_license_information.py
llvm_ir_dataset_utils/tools/collect_textual_ir.py
llvm_ir_dataset_utils/tools/corpus_from_description.py
llvm_ir_dataset_utils/tools/count_values.py
llvm_ir_dataset_utils/tools/delete_folder.py
llvm_ir_dataset_utils/tools/export_deduplicated_corpus.py
llvm_ir_dataset_utils/tools/extract_build_failure_logs.py
llvm_ir_dataset_utils/tools/get_bbs.py
llvm_ir_dataset_utils/tools/get_build_failure_logs.py
llvm_ir_dataset_utils/tools/get_common_constants.py
llvm_ir_dataset_utils/tools/get_julia_packages.py
llvm_ir_dataset_utils/tools/get_spack_package_list.py
llvm_ir_dataset_utils/tools/get_swift_packages.py
llvm_ir_dataset_utils/tools/grep_source.py
llvm_ir_dataset_utils/tools/link_files.py
llvm_ir_dataset_utils/tools/module_statistics.py
llvm_ir_dataset_utils/tools/parse_crates_database.py
llvm_ir_dataset_utils/tools/process_to_parquet.py
llvm_ir_dataset_utils-0.2.dist-info/LICENSE
llvm_ir_dataset_utils-0.2.dist-info/METADATA
llvm_ir_dataset_utils-0.2.dist-info/WHEEL
llvm_ir_dataset_utils-0.2.dist-info/RECORD
