Metadata-Version: 2.1
Name: llvm-ir-dataset-utils
Version: 0.2
Summary: Infrastructure to build LLVM IR-based Datasets.
License: Apache-2.0
Author: Aiden Grossman
Author-email: aidengrossmanpso@gmail.com
Requires-Python: >=3.9,<3.11
Classifier: Development Status :: 2 - Pre-Alpha
Classifier: Intended Audience :: Science/Research
Classifier: License :: OSI Approved :: Apache Software License
Classifier: Programming Language :: Python
Classifier: Programming Language :: Python :: 3
Classifier: Programming Language :: Python :: 3.9
Classifier: Programming Language :: Python :: 3.10
Requires-Dist: absl-py (>=2.1.0,<3.0.0)
Requires-Dist: ml-compiler-opt (>=0.0.1.dev202401270006,<0.0.2)
Requires-Dist: pandas (>=2.2.2,<3.0.0)
Requires-Dist: ray (>=2.20.0,<3.0.0)
Requires-Dist: toml (>=0.10.2,<0.11.0)
